{"execution": {"start_timestamp": "2024-06-07T00:10:42.817Z", "finish_timestamp": "2024-06-07T00:10:53.321Z"}, "runtime": {"name": "wazero", "version": "0.0.0"}, "results": [{"name": "WASI Assemblyscript tests", "duration_s": 0.430832, "failed": 0, "skipped": 0, "passed": 12, "tests": [{"name": "fd_write-to-stdout", "executed": true, "duration_s": 0.03694725036621094, "wasi_functions": [], "failures": []}, {"name": "environ_sizes_get-multiple-variables", "executed": true, "duration_s": 0.03470349311828613, "wasi_functions": [], "failures": []}, {"name": "environ_sizes_get-no-variables", "executed": true, "duration_s": 0.03432512283325195, "wasi_functions": [], "failures": []}, {"name": "args_sizes_get-no-arguments", "executed": true, "duration_s": 0.036986351013183594, "wasi_functions": [], "failures": []}, {"name": "args_sizes_get-multiple-arguments", "executed": true, "duration_s": 0.03378891944885254, "wasi_functions": [], "failures": []}, {"name": "proc_exit-success", "executed": true, "duration_s": 0.03291821479797363, "wasi_functions": [], "failures": []}, {"name": "fd_write-to-invalid-fd", "executed": true, "duration_s": 0.034293413162231445, "wasi_functions": [], "failures": []}, {"name": "proc_exit-failure", "executed": true, "duration_s": 0.032122135162353516, "wasi_functions": [], "failures": []}, {"name": "args_get-multiple-arguments", "executed": true, "duration_s": 0.038095951080322266, "wasi_functions": [], "failures": []}, {"name": "random_get-non-zero-length", "executed": true, "duration_s": 0.035393476486206055, "wasi_functions": [], "failures": []}, {"name": "random_get-zero-length", "executed": true, "duration_s": 0.03983926773071289, "wasi_functions": [], "failures": []}, {"name": "environ_get-multiple-variables", "executed": true, "duration_s": 0.03898882865905762, "wasi_functions": [], "failures": []}]}, {"name": "WASI Rust tests", "duration_s": 9.09552, "failed": 14, "skipped": 0, "passed": 31, "tests": [{"name": "dangling_fd", "executed": true, "duration_s": 0.09728741645812988, "wasi_functions": [], "failures": []}, {"name": "overwrite_preopen", "executed": true, "duration_s": 0.4270763397216797, "wasi_functions": [], "failures": ["0 == 1"]}, {"name": "fd_flags_set", "executed": true, "duration_s": 0.09346365928649902, "wasi_functions": [], "failures": []}, {"name": "remove_directory_trailing_slashes", "executed": true, "duration_s": 0.09616589546203613, "wasi_functions": [], "failures": []}, {"name": "truncation_rights", "executed": true, "duration_s": 0.4105076789855957, "wasi_functions": [], "failures": ["0 == 1"]}, {"name": "clock_time_get", "executed": true, "duration_s": 0.07568717002868652, "wasi_functions": [], "failures": []}, {"name": "path_rename_dir_trailing_slashes", "executed": true, "duration_s": 0.08635902404785156, "wasi_functions": [], "failures": []}, {"name": "file_unbuffered_write", "executed": true, "duration_s": 0.0895993709564209, "wasi_functions": [], "failures": []}, {"name": "fd_advise", "executed": true, "duration_s": 0.09424757957458496, "wasi_functions": [], "failures": []}, {"name": "fd_readdir", "executed": true, "duration_s": 0.1755199432373047, "wasi_functions": [], "failures": []}, {"name": "path_open_missing", "executed": true, "duration_s": 0.08959269523620605, "wasi_functions": [], "failures": []}, {"name": "file_pread_pwrite", "executed": true, "duration_s": 0.09419655799865723, "wasi_functions": [], "failures": []}, {"name": "path_rename", "executed": true, "duration_s": 0.10274600982666016, "wasi_functions": [], "failures": []}, {"name": "path_filestat", "executed": true, "duration_s": 0.43064427375793457, "wasi_functions": [], "failures": ["0 == 1"]}, {"name": "path_symlink_trailing_slashes", "executed": true, "duration_s": 0.10299444198608398, "wasi_functions": [], "failures": []}, {"name": "file_truncation", "executed": true, "duration_s": 0.0878746509552002, "wasi_functions": [], "failures": []}, {"name": "stdio", "executed": true, "duration_s": 0.40970277786254883, "wasi_functions": [], "failures": ["0 == 1"]}, {"name": "path_open_create_existing", "executed": true, "duration_s": 0.08884859085083008, "wasi_functions": [], "failures": []}, {"name": "path_link", "executed": true, "duration_s": 0.43924736976623535, "wasi_functions": [], "failures": ["0 == 1"]}, {"name": "file_allocate", "executed": true, "duration_s": 0.09475421905517578, "wasi_functions": [], "failures": []}, {"name": "path_open_nonblock", "executed": true, "duration_s": 0.08838486671447754, "wasi_functions": [], "failures": []}, {"name": "symlink_loop", "executed": true, "duration_s": 0.09366536140441895, "wasi_functions": [], "failures": []}, {"name": "dir_fd_op_failures", "executed": true, "duration_s": 0.44447827339172363, "wasi_functions": [], "failures": ["0 == 1"]}, {"name": "path_open_preopen", "executed": true, "duration_s": 0.4549098014831543, "wasi_functions": [], "failures": ["0 == 1"]}, {"name": "sched_yield", "executed": true, "duration_s": 0.07633352279663086, "wasi_functions": [], "failures": []}, {"name": "interesting_paths", "executed": true, "duration_s": 0.09128022193908691, "wasi_functions": [], "failures": []}, {"name": "directory_seek", "executed": true, "duration_s": 0.08938169479370117, "wasi_functions": [], "failures": []}, {"name": "path_open_read_write", "executed": true, "duration_s": 0.38169288635253906, "wasi_functions": [], "failures": ["0 == 1"]}, {"name": "remove_nonempty_directory", "executed": true, "duration_s": 0.0877542495727539, "wasi_functions": [], "failures": []}, {"name": "big_random_buf", "executed": true, "duration_s": 0.08009123802185059, "wasi_functions": [], "failures": []}, {"name": "isatty", "executed": true, "duration_s": 0.08671855926513672, "wasi_functions": [], "failures": []}, {"name": "renumber", "executed": true, "duration_s": 0.4185981750488281, "wasi_functions": [], "failures": ["0 == 1"]}, {"name": "path_open_dirfd_not_dir", "executed": true, "duration_s": 0.08790278434753418, "wasi_functions": [], "failures": []}, {"name": "fd_filestat_set", "executed": true, "duration_s": 0.08785271644592285, "wasi_functions": [], "failures": []}, {"name": "symlink_create", "executed": true, "duration_s": 0.4079771041870117, "wasi_functions": [], "failures": ["0 == 1"]}, {"name": "fd_fdstat_set_rights", "executed": true, "duration_s": 0.44629621505737305, "wasi_functions": [], "failures": ["0 == 1"]}, {"name": "symlink_filestat", "executed": true, "duration_s": 0.4181642532348633, "wasi_functions": [], "failures": ["0 == 1"]}, {"name": "file_seek_tell", "executed": true, "duration_s": 0.09179925918579102, "wasi_functions": [], "failures": []}, {"name": "path_exists", "executed": true, "duration_s": 0.0887901782989502, "wasi_functions": [], "failures": []}, {"name": "readlink", "executed": true, "duration_s": 0.4152805805206299, "wasi_functions": [], "failures": ["0 == 1"]}, {"name": "unlink_file_trailing_slashes", "executed": true, "duration_s": 0.10136866569519043, "wasi_functions": [], "failures": []}, {"name": "poll_oneoff_stdio", "executed": true, "duration_s": 0.6769649982452393, "wasi_functions": [], "failures": ["0 == 1"]}, {"name": "dangling_symlink", "executed": true, "duration_s": 0.0953819751739502, "wasi_functions": [], "failures": []}, {"name": "nofollow_errors", "executed": true, "duration_s": 0.09273219108581543, "wasi_functions": [], "failures": []}, {"name": "close_preopen", "executed": true, "duration_s": 0.08945274353027344, "wasi_functions": [], "failures": []}]}, {"name": "WASI C tests", "duration_s": 0.912431, "failed": 2, "skipped": 0, "passed": 12, "tests": [{"name": "pwrite-with-access", "executed": true, "duration_s": 0.06679630279541016, "wasi_functions": [], "failures": []}, {"name": "pread-with-access", "executed": true, "duration_s": 0.06865882873535156, "wasi_functions": [], "failures": []}, {"name": "fdopendir-with-access", "executed": true, "duration_s": 0.0715031623840332, "wasi_functions": [], "failures": []}, {"name": "lseek", "executed": true, "duration_s": 0.06927895545959473, "wasi_functions": [], "failures": []}, {"name": "clock_gettime-realtime", "executed": true, "duration_s": 0.05691170692443848, "wasi_functions": [], "failures": []}, {"name": "clock_getres-monotonic", "executed": true, "duration_s": 0.061850547790527344, "wasi_functions": [], "failures": []}, {"name": "clock_gettime-monotonic", "executed": true, "duration_s": 0.06013822555541992, "wasi_functions": [], "failures": []}, {"name": "sock_shutdown-invalid_fd", "executed": true, "duration_s": 0.05942988395690918, "wasi_functions": [], "failures": []}, {"name": "fopen-with-no-access", "executed": true, "duration_s": 0.06777477264404297, "wasi_functions": [], "failures": []}, {"name": "sock_shutdown-not_sock", "executed": true, "duration_s": 0.06182694435119629, "wasi_functions": [], "failures": ["0 == 1"]}, {"name": "pwrite-with-append", "executed": true, "duration_s": 0.06774401664733887, "wasi_functions": [], "failures": ["0 == 1"]}, {"name": "stat-dev-ino", "executed": true, "duration_s": 0.0647742748260498, "wasi_functions": [], "failures": []}, {"name": "fopen-with-access", "executed": true, "duration_s": 0.07102084159851074, "wasi_functions": [], "failures": []}, {"name": "clock_getres-realtime", "executed": true, "duration_s": 0.06148171424865723, "wasi_functions": [], "failures": []}]}]}