{"execution": {"start_timestamp": "2023-04-21T00:07:20.901Z", "finish_timestamp": "2023-04-21T00:07:24.005Z"}, "runtime": {"name": "wasmtime-cli", "version": "8.0.0"}, "results": [{"name": "WASI Assemblyscript tests", "duration_s": 0.512065, "failed": 0, "skipped": 0, "passed": 12, "tests": [{"name": "fd_write-to-invalid-fd", "executed": true, "duration_s": 0.04181027412414551, "wasi_functions": [], "failures": []}, {"name": "environ_sizes_get-multiple-variables", "executed": true, "duration_s": 0.04224133491516113, "wasi_functions": [], "failures": []}, {"name": "args_get-multiple-arguments", "executed": true, "duration_s": 0.047647953033447266, "wasi_functions": [], "failures": []}, {"name": "args_sizes_get-no-arguments", "executed": true, "duration_s": 0.04282045364379883, "wasi_functions": [], "failures": []}, {"name": "random_get-non-zero-length", "executed": true, "duration_s": 0.04162454605102539, "wasi_functions": [], "failures": []}, {"name": "args_sizes_get-multiple-arguments", "executed": true, "duration_s": 0.04051351547241211, "wasi_functions": [], "failures": []}, {"name": "proc_exit-success", "executed": true, "duration_s": 0.03917694091796875, "wasi_functions": [], "failures": []}, {"name": "fd_write-to-stdout", "executed": true, "duration_s": 0.043487548828125, "wasi_functions": [], "failures": []}, {"name": "environ_get-multiple-variables", "executed": true, "duration_s": 0.04689979553222656, "wasi_functions": [], "failures": []}, {"name": "proc_exit-failure", "executed": true, "duration_s": 0.03936481475830078, "wasi_functions": [], "failures": []}, {"name": "environ_sizes_get-no-variables", "executed": true, "duration_s": 0.04026055335998535, "wasi_functions": [], "failures": []}, {"name": "random_get-zero-length", "executed": true, "duration_s": 0.043936967849731445, "wasi_functions": [], "failures": []}]}, {"name": "WASI Rust tests", "duration_s": 1.739427, "failed": 0, "skipped": 0, "passed": 12, "tests": [{"name": "dangling_symlink", "executed": true, "duration_s": 0.14512920379638672, "wasi_functions": [], "failures": []}, {"name": "dangling_fd", "executed": true, "duration_s": 0.14204645156860352, "wasi_functions": [], "failures": []}, {"name": "close_preopen", "executed": true, "duration_s": 0.1355595588684082, "wasi_functions": [], "failures": []}, {"name": "fd_filestat_get", "executed": true, "duration_s": 0.10994100570678711, "wasi_functions": [], "failures": []}, {"name": "fd_filestat_set", "executed": true, "duration_s": 0.1314096450805664, "wasi_functions": [], "failures": []}, {"name": "fd_readdir", "executed": true, "duration_s": 0.2990427017211914, "wasi_functions": [], "failures": []}, {"name": "directory_seek", "executed": true, "duration_s": 0.13431239128112793, "wasi_functions": [], "failures": []}, {"name": "big_random_buf", "executed": true, "duration_s": 0.11387443542480469, "wasi_functions": [], "failures": []}, {"name": "fd_flags_set", "executed": true, "duration_s": 0.13481855392456055, "wasi_functions": [], "failures": []}, {"name": "clock_time_get", "executed": true, "duration_s": 0.10910224914550781, "wasi_functions": [], "failures": []}, {"name": "interesting_paths", "executed": true, "duration_s": 0.13736391067504883, "wasi_functions": [], "failures": []}, {"name": "fd_advise", "executed": true, "duration_s": 0.14447808265686035, "wasi_functions": [], "failures": []}]}, {"name": "WASI C tests", "duration_s": 0.779434, "failed": 0, "skipped": 0, "passed": 11, "tests": [{"name": "fdopendir-with-access", "executed": true, "duration_s": 0.06979036331176758, "wasi_functions": [], "failures": []}, {"name": "pwrite-with-access", "executed": true, "duration_s": 0.07072639465332031, "wasi_functions": [], "failures": []}, {"name": "stat-dev-ino", "executed": true, "duration_s": 0.09340429306030273, "wasi_functions": [], "failures": []}, {"name": "pread-with-access", "executed": true, "duration_s": 0.0697178840637207, "wasi_functions": [], "failures": []}, {"name": "fopen-with-access", "executed": true, "duration_s": 0.07066798210144043, "wasi_functions": [], "failures": []}, {"name": "clock_getres-realtime", "executed": true, "duration_s": 0.06569623947143555, "wasi_functions": [], "failures": []}, {"name": "clock_getres-monotonic", "executed": true, "duration_s": 0.06561684608459473, "wasi_functions": [], "failures": []}, {"name": "fopen-with-no-access", "executed": true, "duration_s": 0.06934022903442383, "wasi_functions": [], "failures": []}, {"name": "clock_gettime-realtime", "executed": true, "duration_s": 0.06607294082641602, "wasi_functions": [], "failures": []}, {"name": "lseek", "executed": true, "duration_s": 0.07100605964660645, "wasi_functions": [], "failures": []}, {"name": "clock_gettime-monotonic", "executed": true, "duration_s": 0.06535220146179199, "wasi_functions": [], "failures": []}]}]}