{"execution": {"start_timestamp": "2025-04-13T00:35:57.111Z", "finish_timestamp": "2025-04-13T00:36:02.613Z"}, "runtime": {"name": "wasmtime", "version": "31.0.0"}, "results": [{"name": "WASI Assemblyscript tests", "duration_s": 0.45585, "failed": 0, "skipped": 0, "passed": 12, "tests": [{"name": "environ_get-multiple-variables", "executed": true, "duration_s": 0.044831275939941406, "wasi_functions": [], "failures": []}, {"name": "fd_write-to-stdout", "executed": true, "duration_s": 0.03912043571472168, "wasi_functions": [], "failures": []}, {"name": "args_get-multiple-arguments", "executed": true, "duration_s": 0.039991140365600586, "wasi_functions": [], "failures": []}, {"name": "proc_exit-failure", "executed": true, "duration_s": 0.03525710105895996, "wasi_functions": [], "failures": []}, {"name": "proc_exit-success", "executed": true, "duration_s": 0.035196781158447266, "wasi_functions": [], "failures": []}, {"name": "environ_sizes_get-multiple-variables", "executed": true, "duration_s": 0.03626394271850586, "wasi_functions": [], "failures": []}, {"name": "args_sizes_get-multiple-arguments", "executed": true, "duration_s": 0.03836417198181152, "wasi_functions": [], "failures": []}, {"name": "fd_write-to-invalid-fd", "executed": true, "duration_s": 0.03661370277404785, "wasi_functions": [], "failures": []}, {"name": "random_get-zero-length", "executed": true, "duration_s": 0.0382390022277832, "wasi_functions": [], "failures": []}, {"name": "environ_sizes_get-no-variables", "executed": true, "duration_s": 0.03688859939575195, "wasi_functions": [], "failures": []}, {"name": "args_sizes_get-no-arguments", "executed": true, "duration_s": 0.03642606735229492, "wasi_functions": [], "failures": []}, {"name": "random_get-non-zero-length", "executed": true, "duration_s": 0.03659319877624512, "wasi_functions": [], "failures": []}]}, {"name": "WASI Rust tests", "duration_s": 4.178725, "failed": 8, "skipped": 0, "passed": 38, "tests": [{"name": "remove_directory_trailing_slashes", "executed": true, "duration_s": 0.10125494003295898, "wasi_functions": [], "failures": ["0 == 134"]}, {"name": "renumber", "executed": true, "duration_s": 0.07967853546142578, "wasi_functions": [], "failures": ["0 == 134"]}, {"name": "file_seek_tell", "executed": true, "duration_s": 0.08497977256774902, "wasi_functions": [], "failures": []}, {"name": "file_pread_pwrite", "executed": true, "duration_s": 0.08270812034606934, "wasi_functions": [], "failures": []}, {"name": "file_allocate", "executed": true, "duration_s": 0.08324885368347168, "wasi_functions": [], "failures": ["0 == 134"]}, {"name": "path_rename_dir_trailing_slashes", "executed": true, "duration_s": 0.07571887969970703, "wasi_functions": [], "failures": []}, {"name": "sched_yield", "executed": true, "duration_s": 0.06269192695617676, "wasi_functions": [], "failures": []}, {"name": "unlink_file_trailing_slashes", "executed": true, "duration_s": 0.08832383155822754, "wasi_functions": [], "failures": []}, {"name": "path_filestat", "executed": true, "duration_s": 0.08435750007629395, "wasi_functions": [], "failures": ["0 == 134"]}, {"name": "overwrite_preopen", "executed": true, "duration_s": 0.0789644718170166, "wasi_functions": [], "failures": []}, {"name": "path_open_missing", "executed": true, "duration_s": 0.07649660110473633, "wasi_functions": [], "failures": []}, {"name": "isatty", "executed": true, "duration_s": 0.07563495635986328, "wasi_functions": [], "failures": []}, {"name": "path_open_create_existing", "executed": true, "duration_s": 0.07744526863098145, "wasi_functions": [], "failures": []}, {"name": "stdio", "executed": true, "duration_s": 0.07816147804260254, "wasi_functions": [], "failures": []}, {"name": "poll_oneoff_stdio", "executed": true, "duration_s": 0.09769582748413086, "wasi_functions": [], "failures": []}, {"name": "symlink_filestat", "executed": true, "duration_s": 0.07784056663513184, "wasi_functions": [], "failures": []}, {"name": "symlink_loop", "executed": true, "duration_s": 0.08282279968261719, "wasi_functions": [], "failures": []}, {"name": "close_preopen", "executed": true, "duration_s": 0.07838797569274902, "wasi_functions": [], "failures": []}, {"name": "clock_time_get", "executed": true, "duration_s": 0.06264781951904297, "wasi_functions": [], "failures": []}, {"name": "path_open_dirfd_not_dir", "executed": true, "duration_s": 0.07671022415161133, "wasi_functions": [], "failures": []}, {"name": "symlink_create", "executed": true, "duration_s": 0.07634401321411133, "wasi_functions": [], "failures": []}, {"name": "path_link", "executed": true, "duration_s": 0.0914008617401123, "wasi_functions": [], "failures": ["0 == 134"]}, {"name": "fstflags_validate", "executed": true, "duration_s": 0.07595443725585938, "wasi_functions": [], "failures": []}, {"name": "dangling_fd", "executed": true, "duration_s": 0.08192110061645508, "wasi_functions": [], "failures": []}, {"name": "path_rename", "executed": true, "duration_s": 0.08904170989990234, "wasi_functions": [], "failures": []}, {"name": "truncation_rights", "executed": true, "duration_s": 0.07947611808776855, "wasi_functions": [], "failures": ["0 == 134"]}, {"name": "directory_seek", "executed": true, "duration_s": 0.07825708389282227, "wasi_functions": [], "failures": []}, {"name": "fd_readdir", "executed": true, "duration_s": 0.5487010478973389, "wasi_functions": [], "failures": []}, {"name": "path_open_nonblock", "executed": true, "duration_s": 0.07484674453735352, "wasi_functions": [], "failures": []}, {"name": "fd_advise", "executed": true, "duration_s": 0.08316850662231445, "wasi_functions": [], "failures": ["0 == 134"]}, {"name": "path_open_read_write", "executed": true, "duration_s": 0.07852530479431152, "wasi_functions": [], "failures": []}, {"name": "dir_fd_op_failures", "executed": true, "duration_s": 0.08857560157775879, "wasi_functions": [], "failures": []}, {"name": "file_unbuffered_write", "executed": true, "duration_s": 0.0778045654296875, "wasi_functions": [], "failures": []}, {"name": "big_random_buf", "executed": true, "duration_s": 0.06658196449279785, "wasi_functions": [], "failures": []}, {"name": "dangling_symlink", "executed": true, "duration_s": 0.08318614959716797, "wasi_functions": [], "failures": []}, {"name": "fd_flags_set", "executed": true, "duration_s": 0.0790557861328125, "wasi_functions": [], "failures": []}, {"name": "path_exists", "executed": true, "duration_s": 0.07655000686645508, "wasi_functions": [], "failures": []}, {"name": "fd_fdstat_set_rights", "executed": true, "duration_s": 0.08162498474121094, "wasi_functions": [], "failures": ["0 == 134"]}, {"name": "path_symlink_trailing_slashes", "executed": true, "duration_s": 0.09170079231262207, "wasi_functions": [], "failures": []}, {"name": "fd_filestat_set", "executed": true, "duration_s": 0.07869458198547363, "wasi_functions": [], "failures": []}, {"name": "file_truncation", "executed": true, "duration_s": 0.07741189002990723, "wasi_functions": [], "failures": []}, {"name": "nofollow_errors", "executed": true, "duration_s": 0.08047771453857422, "wasi_functions": [], "failures": []}, {"name": "readlink", "executed": true, "duration_s": 0.0789039134979248, "wasi_functions": [], "failures": []}, {"name": "path_open_preopen", "executed": true, "duration_s": 0.08870768547058105, "wasi_functions": [], "failures": []}, {"name": "interesting_paths", "executed": true, "duration_s": 0.07982730865478516, "wasi_functions": [], "failures": []}, {"name": "remove_nonempty_directory", "executed": true, "duration_s": 0.07643532752990723, "wasi_functions": [], "failures": []}]}, {"name": "WASI C tests", "duration_s": 0.802285, "failed": 1, "skipped": 0, "passed": 13, "tests": [{"name": "fopen-with-no-access", "executed": true, "duration_s": 0.05694913864135742, "wasi_functions": [], "failures": []}, {"name": "pwrite-with-access", "executed": true, "duration_s": 0.056807756423950195, "wasi_functions": [], "failures": []}, {"name": "clock_getres-realtime", "executed": true, "duration_s": 0.054265499114990234, "wasi_functions": [], "failures": []}, {"name": "sock_shutdown-invalid_fd", "executed": true, "duration_s": 0.05396413803100586, "wasi_functions": [], "failures": []}, {"name": "fopen-with-access", "executed": true, "duration_s": 0.06066274642944336, "wasi_functions": [], "failures": []}, {"name": "clock_gettime-realtime", "executed": true, "duration_s": 0.0538334846496582, "wasi_functions": [], "failures": []}, {"name": "fdopendir-with-access", "executed": true, "duration_s": 0.06021881103515625, "wasi_functions": [], "failures": []}, {"name": "stat-dev-ino", "executed": true, "duration_s": 0.05766177177429199, "wasi_functions": [], "failures": []}, {"name": "lseek", "executed": true, "duration_s": 0.06142473220825195, "wasi_functions": [], "failures": []}, {"name": "clock_getres-monotonic", "executed": true, "duration_s": 0.05407357215881348, "wasi_functions": [], "failures": []}, {"name": "pwrite-with-append", "executed": true, "duration_s": 0.06086397171020508, "wasi_functions": [], "failures": ["0 == 134"]}, {"name": "clock_gettime-monotonic", "executed": true, "duration_s": 0.05442953109741211, "wasi_functions": [], "failures": []}, {"name": "sock_shutdown-not_sock", "executed": true, "duration_s": 0.05388927459716797, "wasi_functions": [], "failures": []}, {"name": "pread-with-access", "executed": true, "duration_s": 0.06079983711242676, "wasi_functions": [], "failures": []}]}]}