{"execution": {"start_timestamp": "2026-01-12T00:03:17.031Z", "finish_timestamp": "2026-01-12T00:03:22.281Z"}, "results": [{"name": "WASI Rust tests", "runtime": {"name": "wasmtime", "version": "42.0.0"}, "duration_s": 0.000389, "failed": 0, "skipped": 0, "passed": 0, "tests": []}, {"name": "WASI Rust tests [wasm32-wasip1]", "runtime": {"name": "wasmtime", "version": "42.0.0"}, "duration_s": 2.995863, "failed": 1, "skipped": 0, "passed": 45, "tests": [{"name": "path_open_preopen", "executed": true, "duration_s": 0.06395816802978516, "wasi_functions": [], "failures": []}, {"name": "directory_seek", "executed": true, "duration_s": 0.051104068756103516, "wasi_functions": [], "failures": []}, {"name": "file_seek_tell", "executed": true, "duration_s": 0.052237749099731445, "wasi_functions": [], "failures": []}, {"name": "path_open_read_write", "executed": true, "duration_s": 0.06700372695922852, "wasi_functions": [], "failures": []}, {"name": "overwrite_preopen", "executed": true, "duration_s": 0.06636357307434082, "wasi_functions": [], "failures": []}, {"name": "symlink_filestat", "executed": true, "duration_s": 0.06489014625549316, "wasi_functions": [], "failures": []}, {"name": "readlink", "executed": true, "duration_s": 0.06838726997375488, "wasi_functions": [], "failures": []}, {"name": "path_open_create_existing", "executed": true, "duration_s": 0.05084586143493652, "wasi_functions": [], "failures": []}, {"name": "poll_oneoff_stdio", "executed": true, "duration_s": 0.06811165809631348, "wasi_functions": [], "failures": []}, {"name": "path_rename_dir_trailing_slashes", "executed": true, "duration_s": 0.04887056350708008, "wasi_functions": [], "failures": []}, {"name": "fd_fdstat_set_rights", "executed": true, "duration_s": 0.05348396301269531, "wasi_functions": [], "failures": []}, {"name": "path_open_missing", "executed": true, "duration_s": 0.05018877983093262, "wasi_functions": [], "failures": []}, {"name": "path_open_dirfd_not_dir", "executed": true, "duration_s": 0.05057072639465332, "wasi_functions": [], "failures": []}, {"name": "file_unbuffered_write", "executed": true, "duration_s": 0.05129599571228027, "wasi_functions": [], "failures": []}, {"name": "interesting_paths", "executed": true, "duration_s": 0.05317401885986328, "wasi_functions": [], "failures": []}, {"name": "path_link", "executed": true, "duration_s": 0.06374526023864746, "wasi_functions": [], "failures": []}, {"name": "path_open_nonblock", "executed": true, "duration_s": 0.049292802810668945, "wasi_functions": [], "failures": []}, {"name": "path_rename", "executed": true, "duration_s": 0.06514906883239746, "wasi_functions": [], "failures": []}, {"name": "fd_advise", "executed": true, "duration_s": 0.050435543060302734, "wasi_functions": [], "failures": []}, {"name": "fd_filestat_set", "executed": true, "duration_s": 0.04955601692199707, "wasi_functions": [], "failures": []}, {"name": "fd_flags_set", "executed": true, "duration_s": 0.052701473236083984, "wasi_functions": [], "failures": []}, {"name": "sched_yield", "executed": true, "duration_s": 0.03711390495300293, "wasi_functions": [], "failures": []}, {"name": "clock_time_get", "executed": true, "duration_s": 0.03955698013305664, "wasi_functions": [], "failures": []}, {"name": "nofollow_errors", "executed": true, "duration_s": 0.05195426940917969, "wasi_functions": [], "failures": []}, {"name": "file_truncation", "executed": true, "duration_s": 0.04961419105529785, "wasi_functions": [], "failures": []}, {"name": "big_random_buf", "executed": true, "duration_s": 0.039591312408447266, "wasi_functions": [], "failures": []}, {"name": "dangling_fd", "executed": true, "duration_s": 0.05573463439941406, "wasi_functions": [], "failures": []}, {"name": "fstflags_validate", "executed": true, "duration_s": 0.049695730209350586, "wasi_functions": [], "failures": []}, {"name": "dangling_symlink", "executed": true, "duration_s": 0.0569305419921875, "wasi_functions": [], "failures": []}, {"name": "path_symlink_trailing_slashes", "executed": true, "duration_s": 0.06445717811584473, "wasi_functions": [], "failures": []}, {"name": "path_exists", "executed": true, "duration_s": 0.0503392219543457, "wasi_functions": [], "failures": []}, {"name": "file_allocate", "executed": true, "duration_s": 0.05188274383544922, "wasi_functions": [], "failures": []}, {"name": "fd_readdir", "executed": true, "duration_s": 0.5306482315063477, "wasi_functions": [], "failures": []}, {"name": "symlink_create", "executed": true, "duration_s": 0.050237417221069336, "wasi_functions": [], "failures": []}, {"name": "unlink_file_trailing_slashes", "executed": true, "duration_s": 0.06276822090148926, "wasi_functions": [], "failures": []}, {"name": "close_preopen", "executed": true, "duration_s": 0.05104708671569824, "wasi_functions": [], "failures": []}, {"name": "path_filestat", "executed": true, "duration_s": 0.05246472358703613, "wasi_functions": [], "failures": []}, {"name": "stdio", "executed": true, "duration_s": 0.05092334747314453, "wasi_functions": [], "failures": []}, {"name": "truncation_rights", "executed": true, "duration_s": 0.051995038986206055, "wasi_functions": [], "failures": []}, {"name": "renumber", "executed": true, "duration_s": 0.05386018753051758, "wasi_functions": [], "failures": []}, {"name": "file_pread_pwrite", "executed": true, "duration_s": 0.05490589141845703, "wasi_functions": [], "failures": []}, {"name": "remove_directory_trailing_slashes", "executed": true, "duration_s": 0.05956149101257324, "wasi_functions": [], "failures": ["0 == 134"]}, {"name": "remove_nonempty_directory", "executed": true, "duration_s": 0.050200700759887695, "wasi_functions": [], "failures": []}, {"name": "dir_fd_op_failures", "executed": true, "duration_s": 0.06298518180847168, "wasi_functions": [], "failures": []}, {"name": "isatty", "executed": true, "duration_s": 0.05163216590881348, "wasi_functions": [], "failures": []}, {"name": "symlink_loop", "executed": true, "duration_s": 0.057532548904418945, "wasi_functions": [], "failures": []}]}, {"name": "WASI Rust tests [wasm32-wasip3]", "runtime": {"name": "wasmtime", "version": "42.0.0"}, "duration_s": 1.757554, "failed": 0, "skipped": 0, "passed": 17, "tests": [{"name": "http-response", "executed": true, "duration_s": 0.10811185836791992, "wasi_functions": [], "failures": []}, {"name": "filesystem-rename", "executed": true, "duration_s": 0.1083672046661377, "wasi_functions": [], "failures": []}, {"name": "filesystem-flags-and-type", "executed": true, "duration_s": 0.10823249816894531, "wasi_functions": [], "failures": []}, {"name": "filesystem-io", "executed": true, "duration_s": 0.1496751308441162, "wasi_functions": [], "failures": []}, {"name": "wall-clock", "executed": true, "duration_s": 0.04358553886413574, "wasi_functions": [], "failures": []}, {"name": "filesystem-hard-links", "executed": true, "duration_s": 0.10137367248535156, "wasi_functions": [], "failures": []}, {"name": "filesystem-advise", "executed": true, "duration_s": 0.1011497974395752, "wasi_functions": [], "failures": []}, {"name": "filesystem-is-same-object", "executed": true, "duration_s": 0.09547543525695801, "wasi_functions": [], "failures": []}, {"name": "multi-clock-wait", "executed": true, "duration_s": 0.09117269515991211, "wasi_functions": [], "failures": []}, {"name": "filesystem-dotdot", "executed": true, "duration_s": 0.10729289054870605, "wasi_functions": [], "failures": []}, {"name": "filesystem-read-directory", "executed": true, "duration_s": 0.10946083068847656, "wasi_functions": [], "failures": []}, {"name": "filesystem-metadata-hash", "executed": true, "duration_s": 0.12955260276794434, "wasi_functions": [], "failures": []}, {"name": "filesystem-open-errors", "executed": true, "duration_s": 0.0881650447845459, "wasi_functions": [], "failures": []}, {"name": "filesystem-stat", "executed": true, "duration_s": 0.11402392387390137, "wasi_functions": [], "failures": []}, {"name": "filesystem-set-size", "executed": true, "duration_s": 0.1022040843963623, "wasi_functions": [], "failures": []}, {"name": "sockets-echo", "executed": true, "duration_s": 0.11527609825134277, "wasi_functions": [], "failures": []}, {"name": "monotonic-clock", "executed": true, "duration_s": 0.07857370376586914, "wasi_functions": [], "failures": []}]}, {"name": "WASI Assemblyscript  tests [wasm32-wasip1]", "runtime": {"name": "wasmtime", "version": "42.0.0"}, "duration_s": 0.107867, "failed": 0, "skipped": 0, "passed": 12, "tests": [{"name": "proc_exit-success", "executed": true, "duration_s": 0.0067441463470458984, "wasi_functions": [], "failures": []}, {"name": "random_get-zero-length", "executed": true, "duration_s": 0.010117769241333008, "wasi_functions": [], "failures": []}, {"name": "args_sizes_get-multiple-arguments", "executed": true, "duration_s": 0.008030891418457031, "wasi_functions": [], "failures": []}, {"name": "random_get-non-zero-length", "executed": true, "duration_s": 0.008480072021484375, "wasi_functions": [], "failures": []}, {"name": "environ_sizes_get-multiple-variables", "executed": true, "duration_s": 0.007879018783569336, "wasi_functions": [], "failures": []}, {"name": "environ_get-multiple-variables", "executed": true, "duration_s": 0.013063669204711914, "wasi_functions": [], "failures": []}, {"name": "proc_exit-failure", "executed": true, "duration_s": 0.006325721740722656, "wasi_functions": [], "failures": []}, {"name": "args_get-multiple-arguments", "executed": true, "duration_s": 0.011666059494018555, "wasi_functions": [], "failures": []}, {"name": "fd_write-to-stdout", "executed": true, "duration_s": 0.010045051574707031, "wasi_functions": [], "failures": []}, {"name": "args_sizes_get-no-arguments", "executed": true, "duration_s": 0.008152246475219727, "wasi_functions": [], "failures": []}, {"name": "fd_write-to-invalid-fd", "executed": true, "duration_s": 0.007757902145385742, "wasi_functions": [], "failures": []}, {"name": "environ_sizes_get-no-variables", "executed": true, "duration_s": 0.007817268371582031, "wasi_functions": [], "failures": []}]}, {"name": "WASI C tests [wasm32-wasip1]", "runtime": {"name": "wasmtime", "version": "42.0.0"}, "duration_s": 0.387645, "failed": 0, "skipped": 0, "passed": 14, "tests": [{"name": "pwrite-with-access", "executed": true, "duration_s": 0.029000520706176758, "wasi_functions": [], "failures": []}, {"name": "clock_getres-realtime", "executed": true, "duration_s": 0.024003028869628906, "wasi_functions": [], "failures": []}, {"name": "fopen-with-access", "executed": true, "duration_s": 0.0305330753326416, "wasi_functions": [], "failures": []}, {"name": "stat-dev-ino", "executed": true, "duration_s": 0.029033660888671875, "wasi_functions": [], "failures": []}, {"name": "clock_gettime-realtime", "executed": true, "duration_s": 0.025014638900756836, "wasi_functions": [], "failures": []}, {"name": "pread-with-access", "executed": true, "duration_s": 0.028638601303100586, "wasi_functions": [], "failures": []}, {"name": "fdopendir-with-access", "executed": true, "duration_s": 0.030293703079223633, "wasi_functions": [], "failures": []}, {"name": "clock_gettime-monotonic", "executed": true, "duration_s": 0.024290800094604492, "wasi_functions": [], "failures": []}, {"name": "fopen-with-no-access", "executed": true, "duration_s": 0.02908635139465332, "wasi_functions": [], "failures": []}, {"name": "clock_getres-monotonic", "executed": true, "duration_s": 0.024733304977416992, "wasi_functions": [], "failures": []}, {"name": "pwrite-with-append", "executed": true, "duration_s": 0.02812337875366211, "wasi_functions": [], "failures": []}, {"name": "lseek", "executed": true, "duration_s": 0.03052687644958496, "wasi_functions": [], "failures": []}, {"name": "sock_shutdown-invalid_fd", "executed": true, "duration_s": 0.02435445785522461, "wasi_functions": [], "failures": []}, {"name": "sock_shutdown-not_sock", "executed": true, "duration_s": 0.025528430938720703, "wasi_functions": [], "failures": []}]}]}