{"execution": {"start_timestamp": "2025-05-08T00:12:33.300Z", "finish_timestamp": "2025-05-08T00:12:36.188Z"}, "runtime": {"name": "iwasm", "version": "2.2.0\n\nAbout"}, "results": [{"name": "WASI Assemblyscript tests", "duration_s": 0.420974, "failed": 0, "skipped": 0, "passed": 12, "tests": [{"name": "proc_exit-failure", "executed": true, "duration_s": 0.03488588333129883, "wasi_functions": [], "failures": []}, {"name": "random_get-zero-length", "executed": true, "duration_s": 0.03453683853149414, "wasi_functions": [], "failures": []}, {"name": "args_sizes_get-multiple-arguments", "executed": true, "duration_s": 0.03465557098388672, "wasi_functions": [], "failures": []}, {"name": "args_get-multiple-arguments", "executed": true, "duration_s": 0.034690141677856445, "wasi_functions": [], "failures": []}, {"name": "proc_exit-success", "executed": true, "duration_s": 0.034119367599487305, "wasi_functions": [], "failures": []}, {"name": "environ_sizes_get-multiple-variables", "executed": true, "duration_s": 0.03588247299194336, "wasi_functions": [], "failures": []}, {"name": "environ_sizes_get-no-variables", "executed": true, "duration_s": 0.03527665138244629, "wasi_functions": [], "failures": []}, {"name": "args_sizes_get-no-arguments", "executed": true, "duration_s": 0.03491091728210449, "wasi_functions": [], "failures": []}, {"name": "environ_get-multiple-variables", "executed": true, "duration_s": 0.03537797927856445, "wasi_functions": [], "failures": []}, {"name": "random_get-non-zero-length", "executed": true, "duration_s": 0.03501391410827637, "wasi_functions": [], "failures": []}, {"name": "fd_write-to-stdout", "executed": true, "duration_s": 0.03499579429626465, "wasi_functions": [], "failures": []}, {"name": "fd_write-to-invalid-fd", "executed": true, "duration_s": 0.034865379333496094, "wasi_functions": [], "failures": []}]}, {"name": "WASI Rust tests", "duration_s": 1.910557, "failed": 0, "skipped": 0, "passed": 46, "tests": [{"name": "remove_nonempty_directory", "executed": true, "duration_s": 0.03956794738769531, "wasi_functions": [], "failures": []}, {"name": "symlink_loop", "executed": true, "duration_s": 0.04025769233703613, "wasi_functions": [], "failures": []}, {"name": "path_rename", "executed": true, "duration_s": 0.04128098487854004, "wasi_functions": [], "failures": []}, {"name": "unlink_file_trailing_slashes", "executed": true, "duration_s": 0.04216146469116211, "wasi_functions": [], "failures": []}, {"name": "path_open_read_write", "executed": true, "duration_s": 0.04050254821777344, "wasi_functions": [], "failures": []}, {"name": "file_seek_tell", "executed": true, "duration_s": 0.04013538360595703, "wasi_functions": [], "failures": []}, {"name": "path_exists", "executed": true, "duration_s": 0.04040384292602539, "wasi_functions": [], "failures": []}, {"name": "big_random_buf", "executed": true, "duration_s": 0.039164066314697266, "wasi_functions": [], "failures": []}, {"name": "nofollow_errors", "executed": true, "duration_s": 0.0403141975402832, "wasi_functions": [], "failures": []}, {"name": "stdio", "executed": true, "duration_s": 0.03927874565124512, "wasi_functions": [], "failures": []}, {"name": "fd_filestat_set", "executed": true, "duration_s": 0.03930544853210449, "wasi_functions": [], "failures": []}, {"name": "fd_advise", "executed": true, "duration_s": 0.03986549377441406, "wasi_functions": [], "failures": []}, {"name": "file_truncation", "executed": true, "duration_s": 0.03911256790161133, "wasi_functions": [], "failures": []}, {"name": "fd_flags_set", "executed": true, "duration_s": 0.040351152420043945, "wasi_functions": [], "failures": []}, {"name": "fd_fdstat_set_rights", "executed": true, "duration_s": 0.040262460708618164, "wasi_functions": [], "failures": []}, {"name": "path_open_nonblock", "executed": true, "duration_s": 0.03890848159790039, "wasi_functions": [], "failures": []}, {"name": "symlink_create", "executed": true, "duration_s": 0.03927135467529297, "wasi_functions": [], "failures": []}, {"name": "clock_time_get", "executed": true, "duration_s": 0.03763937950134277, "wasi_functions": [], "failures": []}, {"name": "poll_oneoff_stdio", "executed": true, "duration_s": 0.04045510292053223, "wasi_functions": [], "failures": []}, {"name": "dangling_fd", "executed": true, "duration_s": 0.039612531661987305, "wasi_functions": [], "failures": []}, {"name": "dangling_symlink", "executed": true, "duration_s": 0.03959774971008301, "wasi_functions": [], "failures": []}, {"name": "sched_yield", "executed": true, "duration_s": 0.03784370422363281, "wasi_functions": [], "failures": []}, {"name": "file_allocate", "executed": true, "duration_s": 0.03985166549682617, "wasi_functions": [], "failures": []}, {"name": "fd_readdir", "executed": true, "duration_s": 0.11687159538269043, "wasi_functions": [], "failures": []}, {"name": "remove_directory_trailing_slashes", "executed": true, "duration_s": 0.040459632873535156, "wasi_functions": [], "failures": []}, {"name": "path_open_preopen", "executed": true, "duration_s": 0.03977084159851074, "wasi_functions": [], "failures": []}, {"name": "truncation_rights", "executed": true, "duration_s": 0.039276123046875, "wasi_functions": [], "failures": []}, {"name": "path_filestat", "executed": true, "duration_s": 0.04011368751525879, "wasi_functions": [], "failures": []}, {"name": "path_symlink_trailing_slashes", "executed": true, "duration_s": 0.041069984436035156, "wasi_functions": [], "failures": []}, {"name": "dir_fd_op_failures", "executed": true, "duration_s": 0.04001736640930176, "wasi_functions": [], "failures": []}, {"name": "path_open_dirfd_not_dir", "executed": true, "duration_s": 0.03910398483276367, "wasi_functions": [], "failures": []}, {"name": "file_pread_pwrite", "executed": true, "duration_s": 0.039721012115478516, "wasi_functions": [], "failures": []}, {"name": "directory_seek", "executed": true, "duration_s": 0.03918766975402832, "wasi_functions": [], "failures": []}, {"name": "isatty", "executed": true, "duration_s": 0.03949451446533203, "wasi_functions": [], "failures": []}, {"name": "overwrite_preopen", "executed": true, "duration_s": 0.03930807113647461, "wasi_functions": [], "failures": []}, {"name": "renumber", "executed": true, "duration_s": 0.039585113525390625, "wasi_functions": [], "failures": []}, {"name": "readlink", "executed": true, "duration_s": 0.039556026458740234, "wasi_functions": [], "failures": []}, {"name": "fstflags_validate", "executed": true, "duration_s": 0.03910064697265625, "wasi_functions": [], "failures": []}, {"name": "path_open_missing", "executed": true, "duration_s": 0.03949427604675293, "wasi_functions": [], "failures": []}, {"name": "path_open_create_existing", "executed": true, "duration_s": 0.03915214538574219, "wasi_functions": [], "failures": []}, {"name": "path_link", "executed": true, "duration_s": 0.04112577438354492, "wasi_functions": [], "failures": []}, {"name": "interesting_paths", "executed": true, "duration_s": 0.039951324462890625, "wasi_functions": [], "failures": []}, {"name": "file_unbuffered_write", "executed": true, "duration_s": 0.0392603874206543, "wasi_functions": [], "failures": []}, {"name": "close_preopen", "executed": true, "duration_s": 0.03911328315734863, "wasi_functions": [], "failures": []}, {"name": "path_rename_dir_trailing_slashes", "executed": true, "duration_s": 0.038903236389160156, "wasi_functions": [], "failures": []}, {"name": "symlink_filestat", "executed": true, "duration_s": 0.03931236267089844, "wasi_functions": [], "failures": []}]}, {"name": "WASI C tests", "duration_s": 0.49688, "failed": 1, "skipped": 0, "passed": 13, "tests": [{"name": "sock_shutdown-invalid_fd", "executed": true, "duration_s": 0.03533220291137695, "wasi_functions": [], "failures": []}, {"name": "clock_getres-realtime", "executed": true, "duration_s": 0.03526782989501953, "wasi_functions": [], "failures": []}, {"name": "sock_shutdown-not_sock", "executed": true, "duration_s": 0.03491067886352539, "wasi_functions": [], "failures": []}, {"name": "pread-with-access", "executed": true, "duration_s": 0.035401105880737305, "wasi_functions": [], "failures": []}, {"name": "stat-dev-ino", "executed": true, "duration_s": 0.03523993492126465, "wasi_functions": [], "failures": []}, {"name": "pwrite-with-append", "executed": true, "duration_s": 0.0353693962097168, "wasi_functions": [], "failures": ["0 == 1"]}, {"name": "clock_gettime-monotonic", "executed": true, "duration_s": 0.03481316566467285, "wasi_functions": [], "failures": []}, {"name": "clock_gettime-realtime", "executed": true, "duration_s": 0.03493809700012207, "wasi_functions": [], "failures": []}, {"name": "fopen-with-no-access", "executed": true, "duration_s": 0.03538823127746582, "wasi_functions": [], "failures": []}, {"name": "fdopendir-with-access", "executed": true, "duration_s": 0.03576183319091797, "wasi_functions": [], "failures": []}, {"name": "lseek", "executed": true, "duration_s": 0.0357515811920166, "wasi_functions": [], "failures": []}, {"name": "fopen-with-access", "executed": true, "duration_s": 0.03597617149353027, "wasi_functions": [], "failures": []}, {"name": "clock_getres-monotonic", "executed": true, "duration_s": 0.035103559494018555, "wasi_functions": [], "failures": []}, {"name": "pwrite-with-access", "executed": true, "duration_s": 0.035729169845581055, "wasi_functions": [], "failures": []}]}]}