{"execution": {"start_timestamp": "2025-08-06T00:14:00.611Z", "finish_timestamp": "2025-08-06T00:14:03.620Z"}, "runtime": {"name": "iwasm", "version": "2.4.1\n\nAbout"}, "results": [{"name": "WASI Assemblyscript tests", "duration_s": 0.460407, "failed": 0, "skipped": 0, "passed": 12, "tests": [{"name": "args_sizes_get-no-arguments", "executed": true, "duration_s": 0.03736233711242676, "wasi_functions": [], "failures": []}, {"name": "args_sizes_get-multiple-arguments", "executed": true, "duration_s": 0.037082672119140625, "wasi_functions": [], "failures": []}, {"name": "environ_sizes_get-multiple-variables", "executed": true, "duration_s": 0.037344932556152344, "wasi_functions": [], "failures": []}, {"name": "fd_write-to-invalid-fd", "executed": true, "duration_s": 0.03733253479003906, "wasi_functions": [], "failures": []}, {"name": "random_get-non-zero-length", "executed": true, "duration_s": 0.03846478462219238, "wasi_functions": [], "failures": []}, {"name": "proc_exit-success", "executed": true, "duration_s": 0.03677248954772949, "wasi_functions": [], "failures": []}, {"name": "fd_write-to-stdout", "executed": true, "duration_s": 0.03859567642211914, "wasi_functions": [], "failures": []}, {"name": "environ_get-multiple-variables", "executed": true, "duration_s": 0.03813457489013672, "wasi_functions": [], "failures": []}, {"name": "random_get-zero-length", "executed": true, "duration_s": 0.03742051124572754, "wasi_functions": [], "failures": []}, {"name": "args_get-multiple-arguments", "executed": true, "duration_s": 0.0384821891784668, "wasi_functions": [], "failures": []}, {"name": "proc_exit-failure", "executed": true, "duration_s": 0.0431063175201416, "wasi_functions": [], "failures": []}, {"name": "environ_sizes_get-no-variables", "executed": true, "duration_s": 0.03833913803100586, "wasi_functions": [], "failures": []}]}, {"name": "WASI Rust tests", "duration_s": 1.953071, "failed": 0, "skipped": 0, "passed": 46, "tests": [{"name": "isatty", "executed": true, "duration_s": 0.04153013229370117, "wasi_functions": [], "failures": []}, {"name": "fd_flags_set", "executed": true, "duration_s": 0.04149889945983887, "wasi_functions": [], "failures": []}, {"name": "big_random_buf", "executed": true, "duration_s": 0.040198326110839844, "wasi_functions": [], "failures": []}, {"name": "dangling_fd", "executed": true, "duration_s": 0.041257381439208984, "wasi_functions": [], "failures": []}, {"name": "close_preopen", "executed": true, "duration_s": 0.04070234298706055, "wasi_functions": [], "failures": []}, {"name": "path_open_nonblock", "executed": true, "duration_s": 0.04012250900268555, "wasi_functions": [], "failures": []}, {"name": "file_unbuffered_write", "executed": true, "duration_s": 0.0401921272277832, "wasi_functions": [], "failures": []}, {"name": "interesting_paths", "executed": true, "duration_s": 0.041940927505493164, "wasi_functions": [], "failures": []}, {"name": "path_open_missing", "executed": true, "duration_s": 0.039992570877075195, "wasi_functions": [], "failures": []}, {"name": "path_filestat", "executed": true, "duration_s": 0.042937278747558594, "wasi_functions": [], "failures": []}, {"name": "fstflags_validate", "executed": true, "duration_s": 0.04027748107910156, "wasi_functions": [], "failures": []}, {"name": "renumber", "executed": true, "duration_s": 0.041174888610839844, "wasi_functions": [], "failures": []}, {"name": "stdio", "executed": true, "duration_s": 0.04082465171813965, "wasi_functions": [], "failures": []}, {"name": "remove_nonempty_directory", "executed": true, "duration_s": 0.04084444046020508, "wasi_functions": [], "failures": []}, {"name": "path_rename", "executed": true, "duration_s": 0.04239964485168457, "wasi_functions": [], "failures": []}, {"name": "file_allocate", "executed": true, "duration_s": 0.04119443893432617, "wasi_functions": [], "failures": []}, {"name": "fd_advise", "executed": true, "duration_s": 0.042716264724731445, "wasi_functions": [], "failures": []}, {"name": "path_symlink_trailing_slashes", "executed": true, "duration_s": 0.041944026947021484, "wasi_functions": [], "failures": []}, {"name": "symlink_filestat", "executed": true, "duration_s": 0.04096031188964844, "wasi_functions": [], "failures": []}, {"name": "path_rename_dir_trailing_slashes", "executed": true, "duration_s": 0.04073691368103027, "wasi_functions": [], "failures": []}, {"name": "symlink_loop", "executed": true, "duration_s": 0.040480852127075195, "wasi_functions": [], "failures": []}, {"name": "truncation_rights", "executed": true, "duration_s": 0.040122032165527344, "wasi_functions": [], "failures": []}, {"name": "unlink_file_trailing_slashes", "executed": true, "duration_s": 0.04119229316711426, "wasi_functions": [], "failures": []}, {"name": "sched_yield", "executed": true, "duration_s": 0.039931297302246094, "wasi_functions": [], "failures": []}, {"name": "path_open_read_write", "executed": true, "duration_s": 0.041290283203125, "wasi_functions": [], "failures": []}, {"name": "path_open_create_existing", "executed": true, "duration_s": 0.0400998592376709, "wasi_functions": [], "failures": []}, {"name": "file_pread_pwrite", "executed": true, "duration_s": 0.04049968719482422, "wasi_functions": [], "failures": []}, {"name": "path_exists", "executed": true, "duration_s": 0.04008626937866211, "wasi_functions": [], "failures": []}, {"name": "directory_seek", "executed": true, "duration_s": 0.03994917869567871, "wasi_functions": [], "failures": []}, {"name": "path_open_dirfd_not_dir", "executed": true, "duration_s": 0.0397796630859375, "wasi_functions": [], "failures": []}, {"name": "readlink", "executed": true, "duration_s": 0.04004406929016113, "wasi_functions": [], "failures": []}, {"name": "overwrite_preopen", "executed": true, "duration_s": 0.04007911682128906, "wasi_functions": [], "failures": []}, {"name": "clock_time_get", "executed": true, "duration_s": 0.0384526252746582, "wasi_functions": [], "failures": []}, {"name": "fd_readdir", "executed": true, "duration_s": 0.1148068904876709, "wasi_functions": [], "failures": []}, {"name": "dir_fd_op_failures", "executed": true, "duration_s": 0.04133963584899902, "wasi_functions": [], "failures": []}, {"name": "fd_fdstat_set_rights", "executed": true, "duration_s": 0.04039573669433594, "wasi_functions": [], "failures": []}, {"name": "nofollow_errors", "executed": true, "duration_s": 0.04020214080810547, "wasi_functions": [], "failures": []}, {"name": "dangling_symlink", "executed": true, "duration_s": 0.04026389122009277, "wasi_functions": [], "failures": []}, {"name": "remove_directory_trailing_slashes", "executed": true, "duration_s": 0.040450096130371094, "wasi_functions": [], "failures": []}, {"name": "file_truncation", "executed": true, "duration_s": 0.03952503204345703, "wasi_functions": [], "failures": []}, {"name": "poll_oneoff_stdio", "executed": true, "duration_s": 0.04165339469909668, "wasi_functions": [], "failures": []}, {"name": "symlink_create", "executed": true, "duration_s": 0.03982138633728027, "wasi_functions": [], "failures": []}, {"name": "path_open_preopen", "executed": true, "duration_s": 0.04074692726135254, "wasi_functions": [], "failures": []}, {"name": "fd_filestat_set", "executed": true, "duration_s": 0.039407968521118164, "wasi_functions": [], "failures": []}, {"name": "path_link", "executed": true, "duration_s": 0.04158353805541992, "wasi_functions": [], "failures": []}, {"name": "file_seek_tell", "executed": true, "duration_s": 0.040307044982910156, "wasi_functions": [], "failures": []}]}, {"name": "WASI C tests", "duration_s": 0.532745, "failed": 1, "skipped": 0, "passed": 13, "tests": [{"name": "stat-dev-ino", "executed": true, "duration_s": 0.03790855407714844, "wasi_functions": [], "failures": []}, {"name": "pread-with-access", "executed": true, "duration_s": 0.03803300857543945, "wasi_functions": [], "failures": []}, {"name": "clock_gettime-realtime", "executed": true, "duration_s": 0.03735685348510742, "wasi_functions": [], "failures": []}, {"name": "fopen-with-no-access", "executed": true, "duration_s": 0.037650108337402344, "wasi_functions": [], "failures": []}, {"name": "lseek", "executed": true, "duration_s": 0.03792285919189453, "wasi_functions": [], "failures": []}, {"name": "fopen-with-access", "executed": true, "duration_s": 0.037935733795166016, "wasi_functions": [], "failures": []}, {"name": "sock_shutdown-invalid_fd", "executed": true, "duration_s": 0.03769540786743164, "wasi_functions": [], "failures": []}, {"name": "pwrite-with-append", "executed": true, "duration_s": 0.03856348991394043, "wasi_functions": [], "failures": ["0 == 1"]}, {"name": "fdopendir-with-access", "executed": true, "duration_s": 0.038779258728027344, "wasi_functions": [], "failures": []}, {"name": "clock_gettime-monotonic", "executed": true, "duration_s": 0.03777265548706055, "wasi_functions": [], "failures": []}, {"name": "pwrite-with-access", "executed": true, "duration_s": 0.03856468200683594, "wasi_functions": [], "failures": []}, {"name": "clock_getres-monotonic", "executed": true, "duration_s": 0.03796744346618652, "wasi_functions": [], "failures": []}, {"name": "clock_getres-realtime", "executed": true, "duration_s": 0.037489891052246094, "wasi_functions": [], "failures": []}, {"name": "sock_shutdown-not_sock", "executed": true, "duration_s": 0.037178993225097656, "wasi_functions": [], "failures": []}]}]}